gempaterkini/__init__.py
simple_eartquake_info-0.1.0.dist-info/LICENSE
simple_eartquake_info-0.1.0.dist-info/METADATA
simple_eartquake_info-0.1.0.dist-info/WHEEL
simple_eartquake_info-0.1.0.dist-info/top_level.txt
simple_eartquake_info-0.1.0.dist-info/RECORD
