Metadata-Version: 2.1
Name: simple-eartquake-info
Version: 0.1.0
Summary: This package will get the simple info of eartquake from BMKG
Home-page: https://github.com/rc4dayyan/simple-eartquake-info
Author: rc4dayyan
Author-email: rifadayyan@gmail.com
License: UNKNOWN
Project-URL: Source, https://github.com/rc4dayyan/simple-eartquake-info
Keywords: earthquake,earthquake info
Platform: UNKNOWN
Classifier: Development Status :: 5 - Production/Stable
Classifier: Intended Audience :: Developers
Classifier: Topic :: Software Development :: Build Tools
Classifier: License :: OSI Approved :: GNU General Public License v3 (GPLv3)
Classifier: Programming Language :: Python :: 3
Requires-Python: >=3.6, <4
License-File: LICENSE
